PerSent/CommentAnalyzer.py
PerSent/SentimentAnalyzer.py
PerSent/__init__.py
PerSent/models/classifier.joblib
PerSent/models/weighted_sentiment_model.joblib
PerSent/models/word2vec.model
persent-1.3.3.dist-info/METADATA
persent-1.3.3.dist-info/WHEEL
persent-1.3.3.dist-info/top_level.txt
persent-1.3.3.dist-info/RECORD
